{"children":[{"name":".dockerignore","size":3},{"name":".editorconfig","size":22},{"name":".gitignore","size":12},{"name":".jshintignore","size":5},{"name":".jshintrc","size":185},{"name":".linthub.yml","size":1},{"name":".meteor","children":[{"name":".finished-upgraders","size":13},{"name":".gitignore","size":1},{"name":"packages","size":90},{"name":"platforms","size":2},{"name":"release","size":1},{"name":"versions","size":195}]},{"name":".travis.yml","size":12},{"name":"CONTRIBUTING.md","size":264},{"name":"Dockerfile","size":5},{"name":"LICENSE","size":21},{"name":"README.md","size":79},{"name":"both","children":[{"name":"catalogue.js","size":26},{"name":"collections","children":[{"name":"_messages.js","size":5},{"name":"_schemas.js","size":2},{"name":"apiBackendRatings.js","size":31},{"name":"apiBacklog.js","size":114},{"name":"apiMetadata.js","size":91},{"name":"apiUmbrellaAdmins.js","size":58},{"name":"apiUmbrellaUsers.js","size":72},{"name":"backend.js","size":784},{"name":"backendConfigurations.js","size":29},{"name":"bookmark.js","size":8},{"name":"branding.js","size":94},{"name":"coverPhoto.js","size":33},{"name":"feedback.js","size":87},{"name":"feedbackAnswers.js","size":40},{"name":"feedbackVotes.js","size":42},{"name":"helpers","children":[{"name":"users.js","size":6}]},{"name":"projectLogo.js","size":33},{"name":"rateLimit.js","size":34},{"name":"roles.js","size":7},{"name":"settings.js","size":172},{"name":"users.js","size":84}]},{"name":"contactForm.js","size":30}]},{"name":"client","children":[{"name":"helpers.js","size":17},{"name":"layouts","children":[{"name":"home_layout","children":[{"name":"home_layout.html","size":5},{"name":"search.less","size":31}]},{"name":"master_layout","children":[{"name":"adminLTE.js","size":20},{"name":"master_layout.html","size":15},{"name":"master_layout.js","size":21},{"name":"navbar","children":[{"name":"navbar.html","size":50},{"name":"navbar.js","size":24},{"name":"navbar.less","size":20},{"name":"search","children":[{"name":"search.html","size":41},{"name":"search.js","size":116}]}]},{"name":"sidebar","children":[{"name":"sidebar.html","size":46},{"name":"sidebar.js","size":16},{"name":"sidebar.less","size":10}]}]},{"name":"shared","children":[{"name":"userMenu.html","size":15}]}]},{"name":"lib","children":[{"name":"AdminLTE","children":[{"name":"css","children":[{"name":"AdminLTE.min.css","size":7},{"name":"skins","children":[{"name":"_all-skins.min.css","size":1}]}]}]},{"name":"chartsjs","children":[{"name":"crossfilter.js","size":1383},{"name":"d3.js","size":9466},{"name":"dc.css","size":319},{"name":"dc.js","size":9511}]}]},{"name":"shared","children":[{"name":"helpers.js","size":3},{"name":"loading.html","size":2},{"name":"not_authorized.html","size":11},{"name":"not_found.html","size":14},{"name":"searchField","children":[{"name":"search_field.html","size":17}]}]},{"name":"style","children":[{"name":"bootstrap-variables.less","size":873},{"name":"editor.less","size":27},{"name":"footer.less","size":11},{"name":"global.less","size":71},{"name":"map.less","size":1}]},{"name":"views","children":[{"name":"account","children":[{"name":"account.html","size":81},{"name":"account.js","size":35}]},{"name":"api_backends","children":[{"name":"add","children":[{"name":"steps","children":[{"name":"backend-information.html","size":14},{"name":"base-information.html","size":9},{"name":"prefix-information.html","size":10},{"name":"wizard-bootstrap-steps.html","size":9},{"name":"wizard-bootstrap-steps.less","size":132},{"name":"wizardBootstrapSteps.js","size":13}]},{"name":"wizard.html","size":12},{"name":"wizard.js","size":167}]},{"name":"delete","children":[{"name":"deleteApiBackendConfirmation.html","size":27},{"name":"deleteApiBackendConfirmation.js","size":87}]},{"name":"edit","children":[{"name":"editApiBackend.html","size":13},{"name":"editApiBackend.js","size":58},{"name":"form","children":[{"name":"autoform.js","size":158},{"name":"editApiBackendForm.html","size":70},{"name":"editApiBackendForm.js","size":14},{"name":"editApiBackendForm.less","size":18}]}]},{"name":"form_hints","children":[{"name":"form_hints.js","size":87},{"name":"form_hints.less","size":5}]},{"name":"import_config","children":[{"name":"import.html","size":28},{"name":"import.js","size":174}]},{"name":"import_documentation","children":[{"name":"import.html","size":18},{"name":"import.js","size":76}]},{"name":"manage","children":[{"name":"manage.html","size":84},{"name":"manage.js","size":34},{"name":"manage.less","size":5}]},{"name":"view_api_backend","children":[{"name":"backlog","children":[{"name":"backlog.html","size":27},{"name":"backlog.js","size":17},{"name":"backlog.less","size":16},{"name":"form","children":[{"name":"form.html","size":32},{"name":"form.js","size":36}]},{"name":"item","children":[{"name":"item.html","size":38},{"name":"item.js","size":55}]},{"name":"list","children":[{"name":"list.html","size":10},{"name":"list.less","size":19}]}]},{"name":"details","children":[{"name":"details.html","size":40},{"name":"details.js","size":12},{"name":"matchers","children":[{"name":"matchers.html","size":31}]},{"name":"servers","children":[{"name":"servers.css","size":31},{"name":"servers.html","size":38},{"name":"servers.js","size":13}]},{"name":"status","children":[{"name":"status.html","size":11},{"name":"status.js","size":49}]}]},{"name":"export","children":[{"name":"export.html","size":14},{"name":"export.js","size":30}]},{"name":"feedback","children":[{"name":"feedback_details","children":[{"name":"feedbackDetails.js","size":4},{"name":"feedback_details.html","size":14},{"name":"feedback_details.less","size":17}]},{"name":"feedback_form","children":[{"name":"feedbackForm.js","size":32},{"name":"feedback_form.html","size":21}]},{"name":"feedback_list","children":[{"name":"feedbackList.js","size":25},{"name":"feedback_list.html","size":30},{"name":"feedback_list.less","size":1}]},{"name":"single_feedback","children":[{"name":"singleFeedback.js","size":72},{"name":"single_feedback.css","size":12},{"name":"single_feedback.html","size":28}]}]},{"name":"heading","children":[{"name":"heading.html","size":7}]},{"name":"metadata","children":[{"name":"edit","children":[{"name":"autoform.js","size":27},{"name":"edit.html","size":48}]},{"name":"metadata.html","size":87},{"name":"metadata.js","size":14}]},{"name":"navigation","children":[{"name":"navigation.html","size":43}]},{"name":"usageInstructions","children":[{"name":"usageInstructions.html","size":18},{"name":"usageInstructions.js","size":47},{"name":"usageInstructionsButton.html","size":9}]},{"name":"view_api_backend.html","size":37},{"name":"view_api_backend.js","size":47}]}]},{"name":"bookmarks","children":[{"name":"bookmarks.html","size":10},{"name":"bookmarks.js","size":19}]},{"name":"branding","children":[{"name":"branding.html","size":63},{"name":"branding.js","size":32},{"name":"branding.less","size":26}]},{"name":"catalogue","children":[{"name":"catalogue.html","size":18},{"name":"catalogue.js","size":20},{"name":"favourite","children":[{"name":"favourite.html","size":8},{"name":"favourite.js","size":51}]},{"name":"rating","children":[{"name":"rating.css","size":3},{"name":"rating.html","size":9},{"name":"rating.js","size":168}]},{"name":"viewButton","children":[{"name":"viewButton.html","size":6},{"name":"viewButton.js","size":9}]}]},{"name":"dashboard","children":[{"name":"chart_example","children":[{"name":"chart_layout.html","size":12},{"name":"charts.less","size":5}]},{"name":"charts","children":[{"name":"bar","children":[{"name":"bar.html","size":11},{"name":"move.html","size":11}]},{"name":"charts.css","size":12},{"name":"charts.html","size":21},{"name":"charts.js","size":425},{"name":"filter","children":[{"name":"filter.html","size":48},{"name":"filter.js","size":77}]},{"name":"map","children":[{"name":"map.html","size":10}]},{"name":"table","children":[{"name":"table.html","size":31},{"name":"table.less","size":8}]}]},{"name":"dashboard.html","size":7}]},{"name":"home","children":[{"name":"body","children":[{"name":"homeBody.js","size":22},{"name":"home_body.html","size":153},{"name":"home_body.less","size":114}]},{"name":"contact_form","children":[{"name":"contactForm.js","size":31},{"name":"contact_form.html","size":14}]},{"name":"footer","children":[{"name":"homeFooter.js","size":6},{"name":"home_footer.html","size":32},{"name":"home_footer.less","size":38}]},{"name":"header","children":[]},{"name":"home.html","size":5},{"name":"home.js","size":49},{"name":"home.less","size":32}]},{"name":"latest_api","children":[{"name":"latestApi.html","size":25},{"name":"latestApi.js","size":43},{"name":"latestApi.less","size":38}]},{"name":"profile","children":[{"name":"profile.html","size":19},{"name":"profile.js","size":44},{"name":"profile.less","size":11}]},{"name":"settings","children":[{"name":"settings.html","size":81},{"name":"settings.js","size":56},{"name":"settings.less","size":26}]},{"name":"settings_wizard","children":[{"name":"wizard","children":[{"name":"settingsWizard.css","size":9},{"name":"settingsWizard.html","size":153},{"name":"settingsWizard.js","size":108}]}]},{"name":"status","children":[{"name":"status.html","size":17},{"name":"status.js","size":68}]}]}]},{"name":"config.json.example","size":28},{"name":"docker-compose.yml","size":25},{"name":"docker","children":[{"name":"Dockerfile-development","size":5},{"name":"api-umbrella","children":[{"name":"config","children":[{"name":"api-umbrella.yml.example","size":29}]}]}]},{"name":"documentation","children":[{"name":"collection","children":[{"name":"collection.js","size":17},{"name":"server","children":[{"name":"permissions.js","size":16}]}]},{"name":"design","children":[{"name":"client","children":[{"name":"documentation-editor.html","size":3},{"name":"documentation-editor.js","size":9}]}]},{"name":"manage","children":[{"name":"client","children":[{"name":"autoform.js","size":5},{"name":"manage.css","size":3},{"name":"manage.html","size":51},{"name":"manage.js","size":92},{"name":"uploadButton","children":[{"name":"uploadButton.html","size":3},{"name":"uploadButton.js","size":6}]}]}]},{"name":"server","children":[{"name":"methods.js","size":11},{"name":"publications.js","size":15}]},{"name":"view","children":[{"name":"client","children":[{"name":"documentation.css","size":14},{"name":"documentation.html","size":70},{"name":"documentation.js","size":63},{"name":"resumable.js","size":45}]}]}]},{"name":"lib","children":[{"name":"NCSchemas.js","size":27},{"name":"_config","children":[{"name":"accounts.js","size":70},{"name":"oauth.js","size":13},{"name":"router.js","size":100},{"name":"sAlert.js","size":10}]},{"name":"helperFunctions","children":[{"name":"fileNameEndsWith.js","size":23},{"name":"validateSettings.js","size":57}]},{"name":"i18n","children":[{"name":"en.i18n.json","size":331},{"name":"fi.i18n.json","size":219}]},{"name":"router","children":[{"name":"main.js","size":118},{"name":"users.js","size":17}]}]},{"name":"package.json","size":40},{"name":"packages.json","size":3},{"name":"public","children":[{"name":"favicon.png","size":6},{"name":"img","children":[{"name":"logo.png","size":45},{"name":"opensource.png","size":23},{"name":"sampologo.png","size":95}]},{"name":"swagger","children":[{"name":"css","children":[{"name":"print.css","size":1172},{"name":"reset.css","size":125},{"name":"screen.css","size":1273},{"name":"style.css","size":250},{"name":"typography.css","size":26}]},{"name":"fonts","children":[{"name":"droid-sans-v6-latin-700.eot","size":106},{"name":"droid-sans-v6-latin-700.svg","size":411},{"name":"droid-sans-v6-latin-700.ttf","size":285},{"name":"droid-sans-v6-latin-700.woff","size":96},{"name":"droid-sans-v6-latin-700.woff2","size":34},{"name":"droid-sans-v6-latin-regular.eot","size":115},{"name":"droid-sans-v6-latin-regular.svg","size":403},{"name":"droid-sans-v6-latin-regular.ttf","size":263},{"name":"droid-sans-v6-latin-regular.woff","size":72},{"name":"droid-sans-v6-latin-regular.woff2","size":54}]},{"name":"images","children":[{"name":"explorer_icons.png","size":15},{"name":"favicon-16x16.png","size":4},{"name":"favicon-32x32.png","size":3},{"name":"favicon.ico","size":1},{"name":"logo_small.png","size":4},{"name":"pet_store_api.png","size":4},{"name":"throbber.gif","size":66},{"name":"wordnik_api.png","size":10}]},{"name":"index.html","size":102},{"name":"lib","children":[{"name":"backbone-min.js","size":14},{"name":"handlebars-2.0.0.js","size":27},{"name":"jquery-1.8.0.min.js","size":1},{"name":"jquery.ba-bbq.min.js","size":17},{"name":"jquery.slideto.min.js","size":1},{"name":"jquery.wiggle.min.js","size":7},{"name":"marked.js","size":1271},{"name":"swagger-oauth.js","size":284},{"name":"underscore-min.js","size":5}]},{"name":"o2c.html","size":19},{"name":"swagger-ui.js","size":32151},{"name":"swagger-ui.min.js","size":15},{"name":"swagger.json","size":1}]}]},{"name":"secrets.tar.enc","size":44},{"name":"server","children":[{"name":"accounts.js","size":90},{"name":"githubConfiguration.js","size":32},{"name":"methods","children":[{"name":"accounts.js","size":18},{"name":"additionalConfig.js","size":23},{"name":"apiBackendStatus.js","size":37},{"name":"apiBackends.js","size":110},{"name":"apiBookmarks.js","size":44},{"name":"apiUmbrella.js","size":78},{"name":"contactForm.js","size":21},{"name":"deleteApis.js","size":12},{"name":"elasticSearch.js","size":80},{"name":"feedback.js","size":41},{"name":"importApiConfigs.js","size":110},{"name":"settings.js","size":20},{"name":"status.js","size":123},{"name":"swagger.js","size":18}]},{"name":"migrations.js","size":21},{"name":"publish","children":[{"name":"apiBackendMetadata.js","size":6},{"name":"apiBackendRatings.js","size":34},{"name":"apiBackends.js","size":40},{"name":"apiBacklog.js","size":4},{"name":"apiBookmarks.js","size":9},{"name":"apiDocs.js","size":10},{"name":"apiDocumentation.js","size":10},{"name":"apiUmbrellaAdmins.js","size":3},{"name":"apiUmbrellaUsers.js","size":3},{"name":"branding.js","size":14},{"name":"feedback.js","size":9},{"name":"search.js","size":31},{"name":"settings.js","size":17},{"name":"user.js","size":9}]},{"name":"smtp.js","size":31},{"name":"startup.js","size":40}]}],"name":"root"}
